test6_powerhouse_helper/__init__.py
test6_powerhouse_helper/main.py
test6_powerhouse_helper/AddressBook/Address_Book_Handler.py
test6_powerhouse_helper/AddressBook/addressbook.py
test6_powerhouse_helper/AddressBook/addressbook_data.py
test6_powerhouse_helper/GameGooseKiller/Game_goose.py
test6_powerhouse_helper/GameGooseKiller/font/UA Propisi.ttf
test6_powerhouse_helper/GameGooseKiller/image/Farm-Goose.ico
test6_powerhouse_helper/GameGooseKiller/image/background.png
test6_powerhouse_helper/GameGooseKiller/image/bonus.png
test6_powerhouse_helper/GameGooseKiller/image/boom.png
test6_powerhouse_helper/GameGooseKiller/image/enemy.png
test6_powerhouse_helper/GameGooseKiller/image/gameover.png
test6_powerhouse_helper/GameGooseKiller/image/Goose/1-1.png
test6_powerhouse_helper/GameGooseKiller/image/Goose/1-2.png
test6_powerhouse_helper/GameGooseKiller/image/Goose/1-3.png
test6_powerhouse_helper/GameGooseKiller/image/Goose/1-4.png
test6_powerhouse_helper/GameGooseKiller/image/Goose/1-5.png
test6_powerhouse_helper/GameGooseKiller/image/background/1-1.png
test6_powerhouse_helper/GameGooseKiller/image/background/1-2.png
test6_powerhouse_helper/GameGooseKiller/image/background/1-3.png
test6_powerhouse_helper/NoteBook/Note.py
test6_powerhouse_helper/NoteBook/Note_Book_Handler.py
test6_powerhouse_helper/OtherModules/Sort_Files.py
test6_powerhouse_helper/OtherModules/Сalculator.py
test_6_powerhouse_helper-1.data/data/test6_powerhouse_helper/GameGooseKiller/font/UA Propisi.ttf
test_6_powerhouse_helper-1.data/data/test6_powerhouse_helper/GameGooseKiller/image/Farm-Goose.ico
test_6_powerhouse_helper-1.data/data/test6_powerhouse_helper/GameGooseKiller/image/background.png
test_6_powerhouse_helper-1.data/data/test6_powerhouse_helper/GameGooseKiller/image/bonus.png
test_6_powerhouse_helper-1.data/data/test6_powerhouse_helper/GameGooseKiller/image/boom.png
test_6_powerhouse_helper-1.data/data/test6_powerhouse_helper/GameGooseKiller/image/enemy.png
test_6_powerhouse_helper-1.dist-info/LICENSE
test_6_powerhouse_helper-1.dist-info/METADATA
test_6_powerhouse_helper-1.dist-info/WHEEL
test_6_powerhouse_helper-1.dist-info/entry_points.txt
test_6_powerhouse_helper-1.dist-info/top_level.txt
test_6_powerhouse_helper-1.dist-info/RECORD
